vectormation/__init__.py
vectormation/attributes.py
vectormation/colors.py
vectormation/easings.py
vectormation/morphing.py
vectormation/objects.py
vectormation/style.py
vectormation/tex_file_writing.py
vectormation/utils.py
vectormation/window.py
vectormation-0.0.3.dist-info/METADATA
vectormation-0.0.3.dist-info/WHEEL
vectormation-0.0.3.dist-info/licenses/LICENSE
vectormation-0.0.3.dist-info/RECORD
